{"title": ["Tags - Stack Overflow"], "script": ["https://cdn.sstatic.net/", "{\"options\":{\"locale\":\"en\",\"serverTime\":1686683849,\"routeName\":\"Tags/List\",\"stackAuthUrl\":\"https://stackauth.com\",\"networkMetaHostname\":\"meta.stackexchange.com\",\"site\":{\"name\":\"Stack Overflow\",\"description\":\"Q\\u0026A for professional and enthusiast programmers\",\"isNoticesTabEnabled\":true,\"enableNewTagCreationWarning\":true,\"insertSpaceAfterNameTabCompletion\":false,\"id\":1,\"cookieDomain\":\".stackoverflow.com\",\"childUrl\":\"https://meta.stackoverflow.com\",\"negativeVoteScoreFloor\":null,\"enableSocialMediaInSharePopup\":true,\"protocol\":\"https\"},\"user\":{\"fkey\":\"f013da0d9f43a71cc1cd279a4fb8a28dc102d4389005b0dcbff058cb39628cfc\",\"tid\":\"10bfff8e-3948-3a2f-6eca-bd223e61b57c\",\"rep\":0,\"isAnonymous\":true,\"isAnonymousNetworkWide\":true,\"ab\":{\"collectives_survey\":{\"v\":\"coso_survey\",\"g\":1}}},\"events\":{\"postType\":{\"question\":1},\"postEditionSection\":{\"title\":1,\"body\":2,\"tags\":3}}}}", "{\"settings\":{\"userMessaging\":{\"showNewFeatureNotice\":true},\"tags\":{},\"subscriptions\":{\"defaultBasicMaxTrueUpSeats\":250,\"defaultFreemiumMaxTrueUpSeats\":50,\"defaultMaxTrueUpSeats\":1000},\"snippets\":{\"renderDomain\":\"stacksnippets.net\",\"snippetsEnabled\":true},\"site\":{\"allowImageUploads\":true,\"enableImgurHttps\":true,\"enableUserHovercards\":true,\"forceHttpsImages\":true,\"stacksEditorPreviewEnabled\":true,\"styleCode\":true},\"search\":{},\"questions\":{\"enableQuestionTitleLengthLiveWarning\":true,\"enableSavesFeature\":true,\"maxTitleSize\":150,\"questionTitleLengthStartLiveWarningChars\":50},\"intercom\":{\"appId\":\"inf0secd\",\"hostBaseUrl\":\"https://stacksnippets.net\"},\"paths\":{\"jQueryUICSSPath\":\"https://ajax.googleapis.com/ajax/libs/jqueryui/1.12.0/themes/smoothness/jquery-ui.css\",\"jQueryUIJSPath\":\"https://ajax.googleapis.com/ajax/libs/jqueryui/1.12.0/jquery-ui.min.js\"},\"mentions\":{\"maxNumUsersInDropdown\":50},\"markdown\":{\"enableTables\":true},\"legal\":{\"oneTrustConfigId\":\"c3d9f1e3-55f3-4eba-b268-46cee4c6789c\"},\"flags\":{\"allowRetractingCommentFlags\":true,\"allowRetractingFlags\":true},\"elections\":{\"opaVoteResultsBaseUrl\":\"https://www.opavote.com/results/\"},\"comments\":{},\"accounts\":{\"currentPasswordRequiredForChangingStackIdPassword\":true}}}", "StackExchange.init();", "StackExchange.using.setCacheBreakers({\"Js/adops.en.js\":\"6da43f5e0a84\",\"Js/ask.en.js\":\"\",\"Js/begin-edit-event.en.js\":\"20edbaccceae\",\"Js/copy-transpiled.en.js\":\"2e27bf6a799c\",\"Js/events.en.js\":\"\",\"Js/explore-qlist.en.js\":\"2b1f34938b8b\",\"Js/full-anon.en.js\":\"b057cc6384f8\",\"Js/full.en.js\":\"c7942bddca94\",\"Js/highlightjs-loader.en.js\":\"036aae3dd40c\",\"Js/inline-tag-editing.en.js\":\"8a038866f9a6\",\"Js/keyboard-shortcuts.en.js\":\"107c2ac31497\",\"Js/markdown-it-loader.en.js\":\"5818ef89ff9d\",\"Js/mentions-transpiled.en.js\":\"aaeac2684aa8\",\"Js/moderator.en.js\":\"f7a4ba785325\",\"Js/postCollections-transpiled.en.js\":\"216ffeda5016\",\"Js/post-validation.en.js\":\"d62aa8a95b00\",\"Js/question-editor.en.js\":\"\",\"Js/review-v2-transpiled.en.js\":\"6010e419f0e9\",\"Js/revisions.en.js\":\"e6acc03fd5b5\",\"Js/stacks-editor.en.js\":\"861d60735da7\",\"Js/tageditor.en.js\":\"e5db6df2411b\",\"Js/tageditornew.en.js\":\"cebacb19d403\",\"Js/tagsuggestions.en.js\":\"bd6ec908f2a7\",\"Js/unlimited-transpiled.en.js\":\"7ed67670b600\",\"Js/wmd.en.js\":\"e88b27fdc1bc\",\"Js/snippet-javascript-codemirror.en.js\":\"73fce5cc7219\"});\r\n        StackExchange.using(\"gps\", function() {\r\n             StackExchange.gps.init(false);\r\n        });", "StackExchange.ready(function () { StackExchange.topbar.init(); });\r\n\t\tStackExchange.scrollPadding.setPaddingTop(50, 10);", "StackExchange.ready(function () {\r\n            StackExchange.Notice.announcementBannerInit();\r\n        });", "StackExchange.ready(function() {\r\n            $(\".js-tag-filter\").typeWatch({ highlight:true, wait:500, captureLength: -1, callback: finished });\r\n            \r\n        });\r\n\r\n        var request = null;\r\n        function finished(txt) {\r\n            if (request) { request.abort(); }\r\n            request = $.ajax({\r\n                type: \"POST\",\r\n                url: \"/filter/tags-for-index\",\r\n                data: { \r\n                    filter: txt, \r\n                    tab: 'Popular',\r\n                    namesOnly: $('.js-names-only').length > 0 ? $('.js-names-only').is(':checked') : false,\r\n                    fkey: StackExchange.options.user.fkey \r\n                },\r\n                dataType: \"html\",\r\n                success: function (result) {\r\n                    var domelement = $(result);\r\n                    $(\"#tags_list > *\").remove();\r\n                    $(\"#tags_list\").prepend(domelement);\r\n\r\n                    if (txt == \"\") {\r\n                        $(\".pager\").show();\r\n                    } else\r\n                    {\r\n                        $(\".pager\").hide();\r\n                    }\r\n\r\n                }\r\n            });\r\n        }", "window.dataLayer = window.dataLayer || [];\r\n                function gtag() { dataLayer.push(arguments); }", "StackExchange.ready(function() {\r\n\r\n                var ga3Settings = {\r\n                    autoLink: [\"stackoverflow.blog\",\"info.stackoverflowsolutions.com\",\"stackoverflowsolutions.com\"],\r\n                    sendTitles: true,\r\n                    tracker: window.ga,\r\n                    trackingCodes: [\r\n                        'UA-108242619-1'\r\n                    ],\r\n                    checkDimension: 'dimension42'\r\n                                                    };\r\n\r\n                var customGA4Dimensions = {};\r\n\r\n\r\n                var ga4Settings = {\r\n                    tracker: gtag,\r\n                    trackingCodes: [\r\n                        'G-WCZ03SZFCQ'\r\n                    ],\r\n                    consentsToPerformanceCookies: \"denied\",\r\n                    consentsToTargetingCookies: \"denied\",\r\n                    eventParameters: customGA4Dimensions,\r\n                    checkForAdBlock: true\r\n                };\r\n\r\n                StackExchange.ga.init({ GA3: ga3Settings, GA4: ga4Settings });\r\n\r\n\r\n\r\n\r\n                StackExchange.ga.setDimension('dimension3', 'Tags/List');\r\n\r\n\r\n                StackExchange.ga.setDimension('dimension7', \"1686683849.938844759\");\r\n\r\n                StackExchange.ga.trackPageView();\r\n            });"], "noscript": ["body,.s-topbar{margin-top:1.9em}"], "style": ["body,.s-topbar{margin-top:1.9em}"], "span": ["Stack Overflow", "Stack Overflow", "Public questions & answers", "Stack Overflow for Teams", "Where developers & technologists share private knowledge with coworkers", "Talent", "Build your employer brand", "Advertising", "Reach developers & technologists worldwide", "Stack Overflow", "Meta Stack Overflow", "Questions", "Explore Collectives", "CC BY-SA", "rev\u00a02023.6.13.43492"], "a": ["About", "Products", "For Teams", "About the company", "current community", "help", "chat", "Sign up", "log in", "more stack exchange communities", "company blog", "Log in", "Sign up", "2023 Developer Survey results", "Create a free Team", "Why Teams?", "Learn more about Collectives", "Learn more about Teams", "Show all tag synonyms", "Popular", "Name", "New", "javascript", "382 asked today", "2211 this week", "python", "572 asked today", "3293 this week", "java", "234 asked today", "1333 this week", "c#", "187 asked today", "1135 this week", "php", "135 asked today", "689 this week", "android", "135 asked today", "835 this week", "html", "151 asked today", "874 this week", "jquery", "36 asked today", "157 this week", "c++", "104 asked today", "599 this week", "css", "106 asked today", "669 this week", "ios", "59 asked today", "321 this week", "sql", "86 asked today", "531 this week", "mysql", "69 asked today", "307 this week", "r", "137 asked today", "725 this week", "node.js", "135 asked today", "721 this week", "reactjs", "200 asked today", "1312 this week", "arrays", "39 asked today", "229 this week", "c", "32 asked today", "255 this week", "asp.net", "21 asked today", "129 this week", "json", "49 asked today", "273 this week", "python-3.x", "75 asked today", "449 this week", "ruby-on-rails", "13 asked today", "93 this week", ".net", "54 asked today", "274 this week", "sql-server", "48 asked today", "232 this week", "swift", "52 asked today", "312 this week", "django", "53 asked today", "335 this week", "angular", "65 asked today", "398 this week", "objective-c", "15 asked this week", "67 this month", "pandas", "77 asked today", "393 this week", "excel", "51 asked today", "353 this week", "angularjs", "7 asked today", "41 this week", "regex", "25 asked today", "144 this week", "ruby", "8 asked today", "66 this week", "linux", "48 asked today", "239 this week", "ajax", "73 asked this week", "252 this month", "iphone", "23 asked this week", "73 this month", "2", "3", "4", "5", "1921", "Next", "Stack Overflow", "Questions", "Help", "Products", "Teams", "Advertising", "Collectives", "Talent", "Company", "About", "Press", "Work Here", "Legal", "Privacy Policy", "Terms of Service", "Contact Us", "Cookie Settings", "Cookie Policy", "Stack Exchange Network", "Technology", "Culture & recreation", "Life & arts", "Science", "Professional", "Business", "API", "Data", "Blog", "Facebook", "Twitter", "LinkedIn", "Instagram", "CC BY-SA", "Cookie Policy"], "div": ["Loading\u2026", "Home", "Tags", "Users", "Companies", "Collectives", "Teams", "Teams", "Create free Team", "For questions about programming in ECMAScript (JavaScript/JS) and its different dialects/implementations (except for ActionScript). Note that JavaScript is NOT Java. Include all tags that are relevant\u2026", "2499031 questions", "Python is a multi-paradigm, dynamically typed, multi-purpose programming language. It is designed to be quick to learn, understand, and use, and enforces a clean and uniform syntax. Please note that P\u2026", "2142931 questions", "Java is a high-level object-oriented programming language. Use this tag when you're having problems using or understanding the language itself. This tag is frequently used alongside other tags for lib\u2026", "1899509 questions", "C# (pronounced \"see sharp\") is a high-level, statically typed, multi-paradigm programming language developed by Microsoft. C# code usually targets Microsoft's .NET family of tools and run-times, which\u2026", "1594149 questions", "PHP is an open source, multi-paradigm, dynamically-typed and interpreted scripting language designed initially for server-side web development. Use this tag for questions about programming in the PHP \u2026", "1459541 questions", "Android is Google's mobile operating system, used for programming or developing digital devices (Smartphones, Tablets, Automobiles, TVs, Wear, Glass, IoT). For topics related to Android, use Android-s\u2026", "1405545 questions", "HTML (HyperText Markup Language) is the markup language for creating web pages and other information to be displayed in a web browser. Questions regarding HTML should include a minimal reproducible ex\u2026", "1175608 questions", "jQuery is a JavaScript library. Consider also adding the JavaScript tag. \r\n\r\njQuery is a popular cross-browser JavaScript library that facilitates Document Object Model (DOM) traversal, event handling\u2026", "1034084 questions", "C++ is a general-purpose programming language. Initially, it was designed as an extension to C and has a similar syntax, but it is now a completely different language. Use this tag for questions about\u2026", "795173 questions", "CSS (Cascading Style Sheets) is a representation style sheet language used for describing the look and formatting of HTML (HyperText Markup Language), XML (Extensible Markup Language) documents and SV\u2026", "793591 questions", "iOS is the mobile operating system running on the Apple iPhone, iPod touch, and iPad. Use this tag [ios] for questions related to programming on the iOS platform. Use the related tags [objective-c] an\u2026", "681495 questions", "Structured Query Language (SQL) is a language for querying databases. Questions should include code examples, table structure, sample data, and a tag for the DBMS implementation (e.g. MySQL, PostgreSQ\u2026", "662016 questions", "MySQL is a free, open-source Relational Database Management System (RDBMS) that uses Structured Query Language (SQL).  DO NOT USE this tag for other DBs such as SQL Server, SQLite etc.  Those are diff\u2026", "660360 questions", "R is a free, open-source programming language & software environment for statistical computing, bioinformatics, visualization & general computing.  Please use minimal reproducible examples others can \u2026", "491680 questions", "Node.js is an event-based, non-blocking, asynchronous I/O runtime that uses Google's V8 JavaScript engine and libuv library. It is used for developing applications that make heavy use of the ability t\u2026", "463416 questions", "React is a JavaScript library for building user interfaces. It uses a declarative, component-based paradigm and aims to be efficient and flexible.", "458087 questions", "An array is an ordered linear data structure consisting of a collection of elements (values, variables, or references), each identified by one or more indexes. When asking about specific variants of a\u2026", "413397 questions", "C is a general-purpose programming language used for system programming (OS and embedded), libraries, games and cross-platform. This tag should be used with general questions concerning the C language\u2026", "397065 questions", "ASP.NET is a Microsoft web application development framework that allows programmers to build dynamic web sites, web applications and web services. It is useful to use this tag in conjunction with the\u2026", "373150 questions", "JSON (JavaScript Object Notation) is a serializable data interchange format that is a machine and human readable. Do not use this tag for native JavaScript objects or JavaScript object literals. Befor\u2026", "356526 questions", "DO NOT USE UNLESS YOUR QUESTION IS FOR PYTHON 3 ONLY. Always use alongside the standard [python] tag.", "338864 questions", "Ruby on Rails is an open source full-stack web application framework written in Ruby. It follows the popular MVC framework model and is known for its \"convention over configuration\" approach to applic\u2026", "336929 questions", "Do NOT use for questions about .NET Core - use [.net-core] instead. The .NET framework is a software framework designed mainly for the Microsoft Windows operating system. It includes an implementation\u2026", "331942 questions", "Microsoft SQL Server is a relational database management system (RDBMS). Use this tag for all Microsoft SQL Server editions including Compact, Express, Azure, Fast-track, APS (formerly PDW) and Azure \u2026", "330520 questions", "Swift is a general-purpose programming language developed by Apple Inc first released in 2014 for its platforms and Linux. Swift is open-source. Use the tag only for questions about language features \u2026", "327842 questions", "Django is an open-source server-side web application framework written in Python. It is designed to reduce the effort required to create complex data-driven websites and web applications, with a speci\u2026", "307296 questions", "Questions about Angular (not to be confused with AngularJS), the web framework from Google. Use this tag for Angular questions which are not specific to an individual version. For the older AngularJS \u2026", "296655 questions", "should be used only on questions that are about Objective-C features or depend on code in the language. The tags [cocoa] and [cocoa-touch] should be used to ask about Apple's frameworks or cl\u2026", "292506 questions", "Pandas is a Python library for data manipulation and analysis, e.g. dataframes, multidimensional time series and cross-sectional datasets commonly found in statistics, experimental science results, ec\u2026", "280269 questions", "Only for questions on programming against Excel objects or files, or formula development. You may combine the Excel tag with VBA, VSTO, C#, VB.NET, PowerShell, OLE automation, and other programming re\u2026", "279678 questions", "Use for questions about AngularJS (1.x), the open-source JavaScript framework. Do NOT use this tag for Angular 2 or later versions; instead, use the [angular] tag.", "262792 questions", "Regular expressions provide a declarative language to match patterns within strings. They are commonly used for string validation, parsing, and transformation. Specify the language (PHP, Python, etc) \u2026", "258198 questions", "Ruby is a multi-platform open-source, dynamic object-oriented interpreted language. The [ruby] tag is for questions related to the Ruby language, including its syntax and its libraries. Ruby on Rails \u2026", "228028 questions", "NOTICE: All Linux questions must be related to programming; those that aren't will be closed.\r\n\r\nUse this tag only if your question relates to programming using Linux APIs or Linux-specific behavior, \u2026", "224899 questions", "AJAX (Asynchronous JavaScript and XML) is a technique for creating interactive website user interfaces without the traditional web page refresh or reload. It uses asynchronous data exchange between cl\u2026", "221807 questions", "unless you are addressing Apple's iPhone and/or iPod touch specifically. For questions not dependent on hardware, use the tag [ios]. More tags to consider are [xcode] (but only if \u2026", "221471 questions", "1", "\u2026", ""], "h3": ["your communities"], "li": ["Sign up", "Public", "Questions", "Help", "Teams", "Advertising", "Collectives", "Talent", "About", "Press", "Work Here", "Legal", "Privacy Policy", "Terms of Service", "Contact Us", "Cookie Settings", "Cookie Policy", "Blog", "Facebook", "Twitter", "LinkedIn", "Instagram"], "strong": ["Stack Overflow for Teams", "Teams"], "h5": ["Collectives\u2122 on Stack Overflow", "Stack Overflow", "Products", "Company", "Stack Exchange Network"], "p": ["Find centralized, trusted content and collaborate around the technologies you use most.", "Teams", "Q&A for work", "Connect and share knowledge within a single location that is structured and easy to search.", "A tag is a keyword or label that categorizes your question with other, similar questions. Using the right tags makes it easier for others to find and answer your question.", "Your privacy"], "h1": ["Tags"], "button": ["Accept all cookies", "Necessary cookies only", "Customize settings"]}